flask_optional_routes_2020
