Metadata-Version: 1.1
Name: flask-optional-routes-2020
Version: 0.0.4
Summary: flask optional routes helps for multiple navigation options
Home-page: https://www.lamed-oti2.ml
Author: kobi shutzi
Author-email: UNKNOWN
License: MIT
Platform: UNKNOWN
Classifier: Development Status :: 5 - Production/Stable
Classifier: Intended Audience :: Education
Classifier: Operating System :: Microsoft :: Windows :: Windows 10
Classifier: License :: OSI Approved :: MIT License
Classifier: Programming Language :: Python :: 3
